MANIFEST.in
README.md
README.rst
history.md
setup.py
the.py
test/test_the_block.py
test/test_the_exe.py
test/test_the_magic.py
test/test_the_matchers.py
test/test_the_special_case.py
test/test_the_this.py
the.egg-info/PKG-INFO
the.egg-info/SOURCES.txt
the.egg-info/dependency_links.txt
the.egg-info/top_level.txt