Metadata-Version: 1.0
Name: the
Version: 0.1.4
Summary: rspec/should.js assertion style for python test
Home-page: http://the-py.github.io/the
Author: Yan Wenjun
Author-email: mylastnameisyan@gmail.com
License: MIT
Platform: UNKNOWN
Classifier: License :: OSI Approved :: MIT License
Classifier: Topic :: Software Development :: Libraries
